dash_enterprise_libraries/__init__.py
dash_enterprise_libraries-0.0.1.dist-info/LICENSE
dash_enterprise_libraries-0.0.1.dist-info/METADATA
dash_enterprise_libraries-0.0.1.dist-info/WHEEL
dash_enterprise_libraries-0.0.1.dist-info/top_level.txt
dash_enterprise_libraries-0.0.1.dist-info/RECORD
